bioodo/__init__.py
bioodo/_version.py
bioodo/bamtools.py
bioodo/bcftools.py
bioodo/bwa.py
bioodo/config.py
bioodo/cutadapt.py
bioodo/fastqc.py
bioodo/mapdamage.py
bioodo/pandas.py
bioodo/picard.py
bioodo/qualimap.py
bioodo/rpkmforgenes.py
bioodo/rsem.py
bioodo/rseqc.py
bioodo/samtools.py
bioodo/settings.py
bioodo/sga.py
bioodo/star.py
bioodo/utils.py
bioodo/vsearch.py
bioodo/xls.py
bioodo/data/config.yaml
bioodo/tests/conftest.py
bioodo/tests/test_bamtools.py
bioodo/tests/test_bcftools.py
bioodo/tests/test_bwa.py
bioodo/tests/test_cutadapt.py
bioodo/tests/test_fastqc.py
bioodo/tests/test_mapdamage.py
bioodo/tests/test_odo.py
bioodo/tests/test_pandas.py
bioodo/tests/test_picard.py
bioodo/tests/test_qualimap.py
bioodo/tests/test_rseqc.py
bioodo/tests/test_samtools.py
bioodo/tests/test_sga.py
bioodo/tests/test_star.py
bioodo/tests/test_utils.py
bioodo/tests/test_vsearch.py
bioodo/tests/utils.py
bioodo-0.1.0.dist-info/DESCRIPTION.rst
bioodo-0.1.0.dist-info/METADATA
bioodo-0.1.0.dist-info/RECORD
bioodo-0.1.0.dist-info/WHEEL
bioodo-0.1.0.dist-info/metadata.json
bioodo-0.1.0.dist-info/top_level.txt
