Metadata-Version: 2.0
Name: bioodo
Version: 0.1.0
Summary: odo extensions for use with bioinformatics
Home-page: http://github.com/percyfal/bioodo
Author: Per Unneberg
Author-email: per.unneberg@scilifelab.se
License: MIT
Platform: UNKNOWN
Requires-Dist: blaze
Requires-Dist: odo
Requires-Dist: pandas
